[
  { "name": "わかばシューター", "type": "shouter" },
  { "name": "もみじシューター", "type": "shouter" },
  { "name": "おちばシューター", "type": "shouter" },
  { "name": "スプラシューター", "type": "shouter" },
  { "name": "スプラシューターコラボ", "type": "shouter" },
  { "name": "スプラシューターベッチュー", "type": "shouter" },
  { "name": "N-ZAP85", "type": "shouter" },
  { "name": "N-ZAP89", "type": "shouter" },
  { "name": "N-ZAP83", "type": "shouter" },
  { "name": "シャープマーカー", "type": "shouter" },
  { "name": "シャープマーカーネオ", "type": "shouter" },
  { "name": "ボールドマーカー", "type": "shouter" },
  { "name": "ボールドマーカーネオ", "type": "shouter" },
  { "name": "ボールドマーカー7", "type": "shouter" },
  { "name": ".52ガロン", "type": "shouter" },
  { "name": ".52ガロンデコ", "type": "shouter" },
  { "name": ".52ガロンベッチュー", "type": "shouter" },
  { "name": ".96ガロン", "type": "shouter" },
  { "name": ".96ガロンデコ", "type": "shouter" },
  { "name": "プロモデラーRG", "type": "shouter" },
  { "name": "プロモデラーMG", "type": "shouter" },
  { "name": "プロモデラーPG", "type": "shouter" },
  { "name": "L3リールガン", "type": "shouter" },
  { "name": "L3リールガンD", "type": "shouter" },
  { "name": "L3リールガンベッチュー", "type": "shouter" },
  { "name": "H3リールガン", "type": "shouter" },
  { "name": "H3リールガンD", "type": "shouter" },
  { "name": "H3リールガンチェリー", "type": "shouter" },
  { "name": "プライムシューター", "type": "shouter" },
  { "name": "プライムシューターコラボ", "type": "shouter" },
  { "name": "プライムシューターベッチュー", "type": "shouter" },
  { "name": "ジェットスイーパー", "type": "shouter" },
  { "name": "ジェットスイーパーカスタム", "type": "shouter" },
  { "name": "ボトルガイザー", "type": "shouter" },
  { "name": "ボトルガイザーフォイル", "type": "shouter" },
  { "name": "スプラマニューバー", "type": "dualies" },
  { "name": "スプラマニューバーコラボ", "type": "dualies" },
  { "name": "スプラマニューバーベッチュー", "type": "dualies" },
  { "name": "デュアルスイーパー", "type": "dualies" },
  { "name": "デュアルスイーパーカスタム", "type": "dualies" },
  { "name": "スパッタリー", "type": "dualies" },
  { "name": "スパッタリー・ヒュー", "type": "dualies" },
  { "name": "スパッタリークリア", "type": "dualies" },
  { "name": "クアッドホッパーブラック", "type": "dualies" },
  { "name": "クアッドホッパーホワイト", "type": "dualies" },
  { "name": "ケルビン525", "type": "dualies" },
  { "name": "ケルビン525デコ", "type": "dualies" },
  { "name": "ケルビン525ベッチュー", "type": "dualies" },
  { "name": "スプラチャージャー", "type": "charger" },
  { "name": "スプラチャージャーコラボ", "type": "charger" },
  { "name": "スプラチャージャーベッチュー", "type": "charger" },
  { "name": "スプラスコープ", "type": "charger" },
  { "name": "スプラスコープコラボ", "type": "charger" },
  { "name": "スプラスコープベッチュー", "type": "charger" },
  { "name": "リッター4K", "type": "charger" },
  { "name": "リッター4Kカスタム", "type": "charger" },
  { "name": "4Kスコープ", "type": "charger" },
  { "name": "4Kスコープカスタム", "type": "charger" },
  { "name": "スクイックリンα", "type": "charger" },
  { "name": "スクイックリンβ", "type": "charger" },
  { "name": "スクイックリンγ", "type": "charger" },
  { "name": "14式竹筒銃・甲", "type": "charger" },
  { "name": "14式竹筒銃・乙", "type": "charger" },
  { "name": "14式竹筒銃・丙", "type": "charger" },
  { "name": "ソイチューバー", "type": "charger" },
  { "name": "ソイチューバーカスタム", "type": "charger" },
  { "name": "ノヴァブラスター", "type": "blaster" },
  { "name": "ノヴァブラスターネオ", "type": "blaster" },
  { "name": "ノヴァブラスターベッチュー", "type": "blaster" },
  { "name": "クラッシュブラスター", "type": "blaster" },
  { "name": "クラッシュブラスターネオ", "type": "blaster" },
  { "name": "ホットブラスター", "type": "blaster" },
  { "name": "ホットブラスターカスタム", "type": "blaster" },
  { "name": "ロングブラスター", "type": "blaster" },
  { "name": "ロングブラスターカスタム", "type": "blaster" },
  { "name": "ロングブラスターネクロ", "type": "blaster" },
  { "name": "ラピッドブラスター", "type": "blaster" },
  { "name": "ラピッドブラスターデコ", "type": "blaster" },
  { "name": "ラピッドブラスターベッチュー", "type": "blaster" },
  { "name": "Rブラスターエリート", "type": "blaster" },
  { "name": "Rブラスターエリートデコ", "type": "blaster" },
  { "name": "スプラローラー", "type": "roller" },
  { "name": "スプラローラーコラボ", "type": "roller" },
  { "name": "スプラローラーベッチュー", "type": "roller" },
  { "name": "カーボンローラー", "type": "roller" },
  { "name": "カーボンローラーデコ", "type": "roller" },
  { "name": "ヴァリアブルローラー", "type": "roller" },
  { "name": "ヴァリアブルローラーフォイル", "type": "roller" },
  { "name": "ダイナモローラー", "type": "roller" },
  { "name": "ダイナモローラーテスラ", "type": "roller" },
  { "name": "ダイナモローラーベッチュー", "type": "roller" },
  { "name": "パブロ", "type": "brush" },
  { "name": "パブロ・ヒュー", "type": "brush" },
  { "name": "パーマネント・パブロ", "type": "brush" },
  { "name": "ホクサイ", "type": "brush" },
  { "name": "ホクサイ・ヒュー", "type": "brush" },
  { "name": "ホクサイベッチュー", "type": "brush" },
  { "name": "バケットスロッシャー", "type": "slosher" },
  { "name": "バケットスロッシャーデコ", "type": "slosher" },
  { "name": "バケットスロッシャーソーダ", "type": "slosher" },
  { "name": "ヒッセン", "type": "slosher" },
  { "name": "ヒッセン・ヒュー", "type": "slosher" },
  { "name": "スクリュースロッシャー", "type": "slosher" },
  { "name": "スクリュースロッシャーネオ", "type": "slosher" },
  { "name": "スクリュースロッシャーベッチュー", "type": "slosher" },
  { "name": "オーバーフロッシャー", "type": "slosher" },
  { "name": "オーバーフロッシャーデコ", "type": "slosher" },
  { "name": "エクスプロッシャー", "type": "slosher" },
  { "name": "エクスプロッシャーカスタム", "type": "slosher" },
  { "name": "スプラスピナー", "type": "spinner" },
  { "name": "スプラスピナーコラボ", "type": "spinner" },
  { "name": "スプラスピナーベッチュー", "type": "spinner" },
  { "name": "バレルスピナー", "type": "spinner" },
  { "name": "バレルスピナーデコ", "type": "spinner" },
  { "name": "バレルスピナーリミックス", "type": "spinner" },
  { "name": "ハイドラント", "type": "spinner" },
  { "name": "ハイドラントカスタム", "type": "spinner" },
  { "name": "クーゲルシュライバー", "type": "spinner" },
  { "name": "クーゲルシュライバー・ヒュー", "type": "spinner" },
  { "name": "ノーチラス47", "type": "spinner" },
  { "name": "ノーチラス79", "type": "spinner" },
  { "name": "パラシェルター", "type": "brella" },
  { "name": "パラシェルターソレーラ", "type": "brella" },
  { "name": "スパイガジェット", "type": "brella" },
  { "name": "スパイガジェットソレーラ", "type": "brella" },
  { "name": "スパイガジェットベッチュー", "type": "brella" },
  { "name": "キャンピングシェルター", "type": "brella" },
  { "name": "キャンピングシェルターソレーラ", "type": "brella" },
  { "name": "キャンピングシェルターカーモ", "type": "brella" }
]
